paddledet/LICENSE
paddledet/README.md
paddledet/gaea_paddledet.egg-info/PKG-INFO
paddledet/gaea_paddledet.egg-info/SOURCES.txt
paddledet/gaea_paddledet.egg-info/dependency_links.txt
paddledet/gaea_paddledet.egg-info/requires.txt
paddledet/gaea_paddledet.egg-info/top_level.txt
paddledet/ppdet/__init__.py
paddledet/ppdet/version.py
paddledet/ppdet/core/__init__.py
paddledet/ppdet/core/workspace.py
paddledet/ppdet/core/config/__init__.py
paddledet/ppdet/core/config/schema.py
paddledet/ppdet/core/config/yaml_helpers.py
paddledet/ppdet/data/__init__.py
paddledet/ppdet/data/reader.py
paddledet/ppdet/data/shm_utils.py
paddledet/ppdet/data/utils.py
paddledet/ppdet/data/crop_utils/__init__.py
paddledet/ppdet/data/crop_utils/annotation_cropper.py
paddledet/ppdet/data/crop_utils/chip_box_utils.py
paddledet/ppdet/data/source/__init__.py
paddledet/ppdet/data/source/category.py
paddledet/ppdet/data/source/coco.py
paddledet/ppdet/data/source/coco_pair.py
paddledet/ppdet/data/source/dataset.py
paddledet/ppdet/data/source/keypoint_coco.py
paddledet/ppdet/data/source/mot.py
paddledet/ppdet/data/source/sniper_coco.py
paddledet/ppdet/data/source/voc.py
paddledet/ppdet/data/source/widerface.py
paddledet/ppdet/data/transform/__init__.py
paddledet/ppdet/data/transform/atss_assigner.py
paddledet/ppdet/data/transform/autoaugment_utils.py
paddledet/ppdet/data/transform/batch_operators.py
paddledet/ppdet/data/transform/gridmask_utils.py
paddledet/ppdet/data/transform/keypoint_operators.py
paddledet/ppdet/data/transform/mot_operators.py
paddledet/ppdet/data/transform/op_helper.py
paddledet/ppdet/data/transform/operators.py
paddledet/ppdet/data/transform/rotated_operators.py
paddledet/ppdet/engine/__init__.py
paddledet/ppdet/engine/callbacks.py
paddledet/ppdet/engine/env.py
paddledet/ppdet/engine/export_utils.py
paddledet/ppdet/engine/tracker.py
paddledet/ppdet/engine/trainer.py
paddledet/ppdet/metrics/__init__.py
paddledet/ppdet/metrics/coco_utils.py
paddledet/ppdet/metrics/json_results.py
paddledet/ppdet/metrics/keypoint_metrics.py
paddledet/ppdet/metrics/map_utils.py
paddledet/ppdet/metrics/mcmot_metrics.py
paddledet/ppdet/metrics/metrics.py
paddledet/ppdet/metrics/mot_metrics.py
paddledet/ppdet/metrics/munkres.py
gaea_paddledet-2.5.0.3.dist-info/LICENSE
gaea_paddledet-2.5.0.3.dist-info/METADATA
gaea_paddledet-2.5.0.3.dist-info/WHEEL
gaea_paddledet-2.5.0.3.dist-info/top_level.txt
gaea_paddledet-2.5.0.3.dist-info/RECORD
